py_music_editer/__init__.py
py_music_editer/music.py
py_music_editer-0.1.0a24051001.dist-info/LICENSE
py_music_editer-0.1.0a24051001.dist-info/METADATA
py_music_editer-0.1.0a24051001.dist-info/WHEEL
py_music_editer-0.1.0a24051001.dist-info/top_level.txt
py_music_editer-0.1.0a24051001.dist-info/RECORD
